autohooks/__version__.py
autohooks/api/__init__.py
autohooks/api/git.py
autohooks/api/path.py
autohooks/cli/__init__.py
autohooks/cli/activate.py
autohooks/cli/check.py
autohooks/config.py
autohooks/hooks.py
autohooks/precommit/__init__.py
autohooks/precommit/run.py
autohooks/precommit/template
autohooks/settings.py
autohooks/template.py
autohooks/terminal.py
autohooks/utils.py
autohooks/version.py
autohooks_gk_fork_wip-2.2.1.dev100.dist-info/entry_points.txt
autohooks_gk_fork_wip-2.2.1.dev100.dist-info/LICENSE
autohooks_gk_fork_wip-2.2.1.dev100.dist-info/WHEEL
autohooks_gk_fork_wip-2.2.1.dev100.dist-info/METADATA
autohooks_gk_fork_wip-2.2.1.dev100.dist-info/RECORD
