Metadata-Version: 2.1
Name: autohooks-gk-fork-wip
Version: 2.2.1.dev100
Summary: Library for managing git hooks
Home-page: https://github.com/greenbone/autohooks
License: GPL-3.0-or-later
Keywords: git,formatting,linting,hooks
Author: Greenbone Networks GmbH
Author-email: info@greenbone.net
Requires-Python: >=3.5,<4.0
Classifier: Development Status :: 4 - Beta
Classifier: Environment :: Console
Classifier: Intended Audience :: Developers
Classifier: Intended Audience :: System Administrators
Classifier: License :: OSI Approved :: GNU General Public License v3 or later (GPLv3+)
Classifier: Operating System :: OS Independent
Classifier: Programming Language :: Python :: 3
Classifier: Programming Language :: Python :: 3.5
Classifier: Programming Language :: Python :: 3.6
Classifier: Programming Language :: Python :: 3.7
Classifier: Programming Language :: Python :: 3.8
Classifier: Programming Language :: Python :: 3.9
Classifier: Topic :: Software Development :: Libraries :: Python Modules
Classifier: Topic :: Software Development :: Version Control :: Git
Requires-Dist: colorful (>=0.5.4,<0.6.0)
Requires-Dist: packaging (>=20.3,<21.0)
Requires-Dist: tomlkit (>=0.5.11,<0.6.0)
Project-URL: Repository, https://github.com/greenbone/autohooks
